inventoryManagement/Inventory.py
inventoryManagement/Menu.py
inventoryManagement/Part.py
inventoryManagement/Transaction.py
inventoryManagement/__init__.py
InvManagement-0.5.1.dist-info/METADATA
InvManagement-0.5.1.dist-info/WHEEL
InvManagement-0.5.1.dist-info/top_level.txt
InvManagement-0.5.1.dist-info/RECORD
