Metadata-Version: 2.1
Name: InvManagement
Version: 0.5.1
Summary: A simple inventory management system
Author: Kyle Tiongson, Hans Neil Emnacin
License: MIT
Classifier: Programming Language :: Python :: 3
Classifier: License :: OSI Approved :: MIT License
Classifier: Operating System :: OS Independent
Requires-Python: >=3.6
